lambda_lite/__init__.py
lambda_lite/combinators.py
lambda_lite/typedefs.py
lambda_lite-0.0.3.dist-info/METADATA
lambda_lite-0.0.3.dist-info/WHEEL
lambda_lite-0.0.3.dist-info/licenses/LICENSE
lambda_lite-0.0.3.dist-info/RECORD
